create_license/__init__.py
create_license/templates/apache-2.txt
create_license/templates/bsd-2.txt
create_license/templates/bsd-3.txt
create_license/templates/closed.txt
create_license/templates/gpl-3.txt
create_license/templates/lgpl-3.txt
create_license/templates/mit.txt
create_license/templates/mpl-2.txt
create_license/templates/none.txt
create_license-2.1.1.dist-info/LICENSE
create_license-2.1.1.dist-info/METADATA
create_license-2.1.1.dist-info/WHEEL
create_license-2.1.1.dist-info/entry_points.txt
create_license-2.1.1.dist-info/top_level.txt
create_license-2.1.1.dist-info/RECORD
