Metadata-Version: 2.1
Name: create-license
Version: 2.1.1
Summary: Easily create license files.
Home-page: https://github.com/itsmaxymoo/create-license
Author: Max Loiacono
Author-email: 
License: MIT License
Platform: UNKNOWN
Classifier: Programming Language :: Python :: 3
Classifier: License :: OSI Approved :: MIT License
Classifier: Operating System :: OS Independent
Requires-Python: >=3.6
License-File: LICENSE
